letsdns/__init__.py
letsdns/__main__.py
letsdns/action.py
letsdns/configuration.py
letsdns/core.py
letsdns/crypto.py
letsdns/hetznerapi.py
letsdns/liveupdate.py
letsdns/nsupdate.py
letsdns/tlsa.py
letsdns/util.py
letsdns-1.2.1.dist-info/licenses/LICENSE
letsdns-1.2.1.dist-info/METADATA
letsdns-1.2.1.dist-info/WHEEL
letsdns-1.2.1.dist-info/entry_points.txt
letsdns-1.2.1.dist-info/top_level.txt
letsdns-1.2.1.dist-info/RECORD
