Metadata-Version: 2.4
Name: letsdns
Version: 1.2.1
Summary: Manage DANE TLSA records in DNS servers
Home-page: https://www.letsdns.de
Author: Ralph Seichter
Author-email: author@letsdns.de
Project-URL: Documentation, https://www.letsdns.de
Project-URL: Source, https://github.com/LetsDNS/letsdns
Project-URL: Tracker, https://github.com/LetsDNS/letsdns/issues
Classifier: Development Status :: 5 - Production/Stable
Classifier: License :: OSI Approved :: GNU General Public License v3 or later (GPLv3+)
Classifier: Operating System :: OS Independent
Classifier: Programming Language :: Python :: 3.7
Classifier: Topic :: System :: Systems Administration
Classifier: Topic :: Utilities
Requires-Python: >=3.7
License-File: LICENSE
Requires-Dist: cryptography
Requires-Dist: dnspython
Requires-Dist: requests
Dynamic: license-file
